trouver/__init__.py
trouver/_modidx.py
trouver/_nbdev.py
trouver/core.py
trouver/helper.py
trouver/app/__init__.py
trouver/helper/__init__.py
trouver/helper/alphabet.py
trouver/helper/arxiv.py
trouver/helper/date_and_time.py
trouver/helper/definition_and_notation.py
trouver/helper/files_and_folders.py
trouver/helper/html.py
trouver/helper/latex.py
trouver/helper/numbers.py
trouver/helper/packages.py
trouver/helper/path_accepted_string.py
trouver/helper/regex.py
trouver/helper/tests.py
trouver/helper/topological_sort.py
trouver/helper/latex/__init__.py
trouver/helper/latex/comments.py
trouver/helper/latex/macros_and_commands.py
trouver/latex/__init__.py
trouver/latex/comments.py
trouver/latex/convert.py
trouver/latex/divide.py
trouver/latex/folders.py
trouver/latex/formatting.py
trouver/latex/preamble.py
trouver/markdown/__init__.py
trouver/markdown/markdown/__init__.py
trouver/markdown/markdown/file.py
trouver/markdown/markdown/heading.py
trouver/markdown/obsidian/__init__.py
trouver/markdown/obsidian/footnotes.py
trouver/markdown/obsidian/links.py
trouver/markdown/obsidian/tags.py
trouver/markdown/obsidian/vault.py
trouver/markdown/obsidian/vault_and_links.py
trouver/markdown/obsidian/personal/__init__.py
trouver/markdown/obsidian/personal/authors.py
trouver/markdown/obsidian/personal/index_notes.py
trouver/markdown/obsidian/personal/information_notes.py
trouver/markdown/obsidian/personal/notation.py
trouver/markdown/obsidian/personal/note_processing.py
trouver/markdown/obsidian/personal/note_type.py
trouver/markdown/obsidian/personal/notes.py
trouver/markdown/obsidian/personal/reference.py
trouver/markdown/obsidian/personal/vault.py
trouver/markdown/obsidian/personal/machine_learning/__init__.py
trouver/markdown/obsidian/personal/machine_learning/database_update.py
trouver/markdown/obsidian/personal/machine_learning/definition_and_notation_naming.py
trouver/markdown/obsidian/personal/machine_learning/definition_identification.py
trouver-1.0.1.dist-info/LICENSE
trouver-1.0.1.dist-info/METADATA
trouver-1.0.1.dist-info/WHEEL
trouver-1.0.1.dist-info/entry_points.txt
trouver-1.0.1.dist-info/top_level.txt
trouver-1.0.1.dist-info/RECORD
