Metadata-Version: 2.1
Name: trouver
Version: 1.0.1
Summary: Create and maintain mathematical Obsidian.md notes, and gather data from them to train ML models
Home-page: https://github.com/hyunjongkimmath/trouver
Author: Hyun Jong Kim
Author-email: hyunjongkim96@gmail.com
License: Apache Software License 2.0
Keywords: nbdev jupyter notebook python
Classifier: Development Status :: 4 - Beta
Classifier: Intended Audience :: Developers
Classifier: Natural Language :: English
Classifier: Programming Language :: Python :: 3.10
Classifier: License :: OSI Approved :: Apache Software License
Requires-Python: >=3.10
License-File: LICENSE
Requires-Dist: arxiv
Requires-Dist: bs4
Requires-Dist: datasets
Requires-Dist: deprecated
Requires-Dist: fastai
Requires-Dist: fastcore
Requires-Dist: natsort
Requires-Dist: Levenshtein
Requires-Dist: multiset
Requires-Dist: pandas
Requires-Dist: pyyaml
Requires-Dist: pylatexenc
Requires-Dist: PyQt6
Requires-Dist: regex
Requires-Dist: transformers
Requires-Dist: pathvalidate
Requires-Dist: toml
Provides-Extra: dev
Requires-Dist: torch; extra == "dev"
Requires-Dist: pyinstaller; extra == "dev"
